nokta_ai/__init__.py
nokta_ai/core.py
nokta_ai/cli/__init__.py
nokta_ai/cli/evaluate_constrained.py
nokta_ai/cli/main.py
nokta_ai/cli/test_constrained.py
nokta_ai/cli/train_constrained.py
nokta_ai/models/__init__.py
nokta_ai/models/constrained.py
nokta_ai-0.1.0.dist-info/METADATA
nokta_ai-0.1.0.dist-info/WHEEL
nokta_ai-0.1.0.dist-info/entry_points.txt
nokta_ai-0.1.0.dist-info/top_level.txt
nokta_ai-0.1.0.dist-info/RECORD
