Metadata-Version: 2.4
Name: nokta-ai
Version: 0.1.0
Summary: Turkish Diacritics Restoration with Neural Networks
Author-email: nokta-ai contributors <contributors@nokta-ai.org>
License: MIT
Project-URL: Homepage, https://github.com/armish/nokta-ai
Project-URL: Repository, https://github.com/armish/nokta-ai
Project-URL: Documentation, https://github.com/armish/nokta-ai#readme
Project-URL: Bug Tracker, https://github.com/armish/nokta-ai/issues
Keywords: turkish,nlp,neural-networks,diacritics,restoration
Classifier: Development Status :: 4 - Beta
Classifier: Intended Audience :: Developers
Classifier: Intended Audience :: Science/Research
Classifier: License :: OSI Approved :: MIT License
Classifier: Operating System :: OS Independent
Classifier: Programming Language :: Python :: 3
Classifier: Programming Language :: Python :: 3.9
Classifier: Programming Language :: Python :: 3.10
Classifier: Programming Language :: Python :: 3.11
Classifier: Programming Language :: Python :: 3.12
Classifier: Topic :: Scientific/Engineering :: Artificial Intelligence
Classifier: Topic :: Text Processing :: Linguistic
Requires-Python: >=3.9
Requires-Dist: torch>=2.0.0
Requires-Dist: numpy<2.0.0
Requires-Dist: tqdm>=4.65.0
Requires-Dist: pyyaml>=6.0.0
Provides-Extra: dev
Requires-Dist: pytest>=7.3.0; extra == "dev"
Requires-Dist: black>=23.0.0; extra == "dev"
Requires-Dist: flake8>=6.0.0; extra == "dev"
Requires-Dist: mypy>=1.0.0; extra == "dev"
Requires-Dist: pre-commit>=3.0.0; extra == "dev"
Provides-Extra: data
Requires-Dist: requests>=2.28.0; extra == "data"
